pic_prompt/__init__.py
pic_prompt/pic_prompt.py
pic_prompt/core/__init__.py
pic_prompt/core/errors.py
pic_prompt/core/image_config.py
pic_prompt/core/message_role.py
pic_prompt/core/message_type.py
pic_prompt/core/prompt_config.py
pic_prompt/core/prompt_content.py
pic_prompt/core/prompt_message.py
pic_prompt/images/__init__.py
pic_prompt/images/errors.py
pic_prompt/images/image_data.py
pic_prompt/images/image_loader.py
pic_prompt/images/image_registry.py
pic_prompt/images/image_resizer.py
pic_prompt/images/sources/__init__.py
pic_prompt/images/sources/http_source.py
pic_prompt/images/sources/image_source.py
pic_prompt/images/sources/local_file_source.py
pic_prompt/images/sources/s3_source.py
pic_prompt/integrations/curl/curl_tester.py
pic_prompt/integrations/promptfoo/promptfoo_prompt_builder.py
pic_prompt/providers/__init__.py
pic_prompt/providers/provider.py
pic_prompt/providers/provider_anthropic.py
pic_prompt/providers/provider_factory.py
pic_prompt/providers/provider_gemini.py
pic_prompt/providers/provider_names.py
pic_prompt/providers/provider_openai.py
pic_prompt/utils/logger.py
pic_prompt-1.7.0.dist-info/METADATA
pic_prompt-1.7.0.dist-info/WHEEL
pic_prompt-1.7.0.dist-info/licenses/LICENSE
pic_prompt-1.7.0.dist-info/RECORD
