Metadata-Version: 2.4
Name: pic_prompt
Version: 1.7.0
Summary: A library for building image prompts for OpenAI. Made for integration with LiteLLM.
Project-URL: Homepage, https://github.com/paulbaranowski/pic-prompt
Project-URL: Bug Tracker, https://github.com/paulbaranowski/pic-prompt/issues
Author-email: Paul Baranowski <paulbaranowski@gmail.com>
License-Expression: Apache-2.0
License-File: LICENSE
Classifier: License :: OSI Approved :: Apache Software License
Classifier: Operating System :: OS Independent
Classifier: Programming Language :: Python :: 3
Requires-Python: >=3.8
Requires-Dist: aiohttp>=3.8.0
Requires-Dist: asyncio
Requires-Dist: boto3>=1.26.0
Requires-Dist: litellm>=1.64.1
Requires-Dist: pillow>=10.4.0
Requires-Dist: pytest-env>=1.1.5
Requires-Dist: requests>=2.28.0
Provides-Extra: test
Requires-Dist: pytest-asyncio>=0.20.0; extra == 'test'
Requires-Dist: pytest-cov>=4.0.0; extra == 'test'
Requires-Dist: pytest-mock>=3.14.0; extra == 'test'
Requires-Dist: pytest>=7.0; extra == 'test'
